{
  "dataset": "taxcalc_cps_national",
  "label": "Tax-Calculator public CPS",
  "engine": "taxcalc 6.7.1",
  "year": 2024,
  "source": "Tax-Calculator public CPS (Census CPS-derived)",
  "source_url": "https://github.com/PSLmodels/Tax-Calculator",
  "notes": "Public CPS reliably covers wages, AGI, taxable income, income tax (before/after credits), EITC, refundable CTC, pensions, taxable Social Security, unemployment, qualified dividends, charitable and medical deductions, and taxable interest. Dropped concepts: capital gains and partnership/S-corp income (structurally absent from the public CPS, i.e. zero); SALT, interest, tax-exempt-interest, ordinary-dividend, IRA-distribution, QBI and total-itemized deductions and combined CTC (grand total >40% off BOTH the official IRS value and populace); real estate taxes (taxcalc e18500 is an all-filer input while SOI counts only itemizers' Schedule A). Itemizer subpopulation (SOI table 2.1) reproduced via c04470>0; EITC-return AGI via c59660!=0.",
  "rows": {
    "irs_soi.ty2023.table_2_5.eitc_by_agi_children.three_or_more_qualifying_children.1k_to_2k.eitc_returns@2024": 16459.75,
    "irs_soi.ty2023.table_2_5.eitc_by_agi_children.three_or_more_qualifying_children.1k_to_2k.eitc_total@2024": 10485432.161235407,
    "irs_soi.ty2023.table_2_5.eitc_by_agi_children.no_qualifying_children.18k_to_19k.eitc_returns@2024": 164035.81,
    "irs_soi.ty2022.historic_table_2.us.200k_to_500k.taxable_interest_amount@2024": 14662768375.711252,
    "irs_soi.ty2023.table_2_5.eitc_by_agi_children.three_or_more_qualifying_children.1_to_1k.eitc_returns@2024": 13003.260000000002,
    "irs_soi.ty2022.historic_table_2.us.100k_to_200k.taxable_interest_amount@2024": 15684540267.671833,
    "irs_soi.ty2023.table_2_5.eitc_by_agi_children.three_or_more_qualifying_children.1_to_1k.eitc_total@2024": 4036533.6566249514,
    "irs_soi.ty2022.historic_table_2.us.50k_to_75k.taxable_interest_amount@2024": 5820535763.152224,
    "irs_soi.ty2022.historic_table_2.us.1_to_10k.taxable_interest_amount@2024": 5915031414.315836,
    "irs_soi.ty2022.historic_table_2.us.75k_to_100k.taxable_interest_amount@2024": 5791437120.398719,
    "irs_soi.ty2022.historic_table_2.us.10k_to_25k.taxable_interest_amount@2024": 5021503970.480501,
    "irs_soi.ty2022.historic_table_2.us.500k_to_1m.taxable_interest_amount@2024": 6192311430.420173,
    "irs_soi.ty2022.historic_table_2.us.25k_to_50k.taxable_interest_amount@2024": 5486385121.106762,
    "irs_soi.ty2023.congressional_district_2022.all_returns.us.taxable_interest_amount@2024": 115299057294.62277,
    "irs_soi.ty2022.historic_table_2.us.all.taxable_interest_amount@2024": 115299057294.62277,
    "irs_soi.ty2023.table_2_5.eitc_by_agi_children.no_qualifying_children.total.eitc_returns@2024": 6029278.09,
    "irs_soi.ty2023.table_2_5.eitc_by_agi_children.one_qualifying_child.total.eitc_returns@2024": 5193165.37,
    "irs_soi.ty2023.table_2_5.eitc_by_agi_children.three_or_more_qualifying_children.total.eitc_returns@2024": 3124184.29,
    "irs_soi.ty2023.table_2_5.eitc_by_agi_children.two_qualifying_children.total.eitc_returns@2024": 4306000.71,
    "irs_soi.ty2023.table_2_5.eitc_by_agi_children.no_qualifying_children.total.eitc_total@2024": 2640873402.672373,
    "irs_soi.ty2023.table_2_5.eitc_by_agi_children.one_qualifying_child.total.eitc_total@2024": 16053661548.400658,
    "irs_soi.ty2023.table_2_5.eitc_by_agi_children.three_or_more_qualifying_children.total.eitc_total@2024": 17053488138.67209,
    "irs_soi.ty2023.table_2_5.eitc_by_agi_children.two_qualifying_children.total.eitc_total@2024": 20894073297.705696,
    "irs_soi.ty2023.table_2_5.eitc_by_agi_children.one_qualifying_child.20k_to_25k.eitc_total@2024": 3278092837.840195,
    "irs_soi.ty2023.table_2_5.eitc_by_agi_children.no_qualifying_children.16k_to_17k.eitc_total@2024": 73557222.07763799,
    "irs_soi.ty2023.table_2_5.eitc_by_agi_children.two_qualifying_children.20k_to_25k.eitc_total@2024": 4199467166.8291874,
    "irs_soi.ty2024.filing_season_week47.eitc_by_agi.20k_to_25k.total_earned_income_credit_amount@2024": 10549958547.091057,
    "irs_soi.ty2023.table_2_5.eitc_by_agi_children.no_qualifying_children.13k_to_14k.eitc_total@2024": 193852168.4796733,
    "irs_soi.ty2023.table_2_5.eitc_by_agi_children.two_qualifying_children.20k_to_25k.eitc_returns@2024": 615520.6599999999,
    "irs_soi.ty2023.table_2_5.eitc_by_agi_children.three_or_more_qualifying_children.20k_to_25k.eitc_total@2024": 3025606247.1942987,
    "irs_soi.ty2023.table_2_5.eitc_by_agi_children.no_qualifying_children.15k_to_16k.eitc_total@2024": 112906018.30202883,
    "irs_soi.ty2022.historic_table_2.us.1m_plus.taxable_interest_amount@2024": 50286992238.51165,
    "irs_soi.ty2023.table_2_5.eitc_by_agi_children.two_qualifying_children.16k_to_17k.eitc_returns@2024": 115230.22,
    "irs_soi.ty2023.table_2_5.eitc_by_agi_children.no_qualifying_children.20k_to_25k.eitc_total@2024": 46792295.22737528,
    "irs_soi.ty2023.table_2_5.eitc_by_agi_children.three_or_more_qualifying_children.20k_to_25k.eitc_returns@2024": 392144.26,
    "irs_soi.ty2023.table_2_5.eitc_by_agi_children.three_or_more_qualifying_children.3k_to_4k.eitc_total@2024": 29530163.451825798,
    "irs_soi.ty2023.table_2_5.eitc_by_agi_children.one_qualifying_child.1_to_1k.eitc_total@2024": 5299204.160359318,
    "irs_soi.ty2023.table_2_5.eitc_by_agi_children.two_qualifying_children.16k_to_17k.eitc_total@2024": 745786324.1498371,
    "irs_soi.ty2023.table_2_5.eitc_by_agi_children.three_or_more_qualifying_children.25k_to_30k.eitc_returns@2024": 398939.69000000006,
    "irs_soi.ty2023.table_2_5.eitc_by_agi_children.two_qualifying_children.17k_to_18k.eitc_returns@2024": 97531.95000000001,
    "irs_soi.ty2023.table_2_5.eitc_by_agi_children.two_qualifying_children.17k_to_18k.eitc_total@2024": 652420136.8243246,
    "irs_soi.ty2024.filing_season_week47.eitc_by_agi.20k_to_25k.total_earned_income_credit_returns@2024": 1994571.5300000003,
    "irs_soi.ty2023.table_2_5.eitc_by_agi_children.three_or_more_qualifying_children.25k_to_30k.eitc_total@2024": 2885875269.2511163,
    "irs_soi.ty2023.table_2_5.eitc_by_agi_children.no_qualifying_children.19k_to_20k.eitc_total@2024": 32390991.403345738,
    "irs_soi.ty2023.table_2_5.eitc_by_agi_children.two_qualifying_children.30k_to_35k.eitc_total@2024": 2876864466.788884,
    "irs_soi.ty2023.table_2_5.eitc_by_agi_children.no_qualifying_children.17k_to_18k.eitc_total@2024": 52181447.76385454,
    "irs_soi.ty2023.table_2_5.eitc_by_agi_children.one_qualifying_child.20k_to_25k.eitc_returns@2024": 794996.0900000001,
    "irs_soi.ty2024.filing_season_week47.eitc_by_agi.25k_to_30k.total_earned_income_credit_amount@2024": 8942572525.39012,
    "irs_soi.ty2024.filing_season_week47.eitc_all_returns.earned_income_credit.total_earned_income_credit_amount@2024": 56642096387.45082,
    "irs_soi.ty2023.table_1_4.all.taxable_social_security_amount@2024": 625887711518.7126,
    "irs_soi.ty2023.table_2_5.eitc_by_agi_children.two_qualifying_children.25k_to_30k.eitc_total@2024": 3670710641.793679,
    "irs_soi.ty2022.historic_table_2.us.1m_plus.taxable_interest_returns@2024": 564723.03,
    "irs_soi.ty2023.table_2_5.eitc_by_agi_children.three_or_more_qualifying_children.50k_plus.eitc_total@2024": 617689396.6929736,
    "irs_soi.ty2023.table_2_5.eitc_by_agi_children.one_qualifying_child.2k_to_3k.eitc_total@2024": 37283236.429366305,
    "irs_soi.ty2023.table_2_5.eitc_by_agi_children.one_qualifying_child.30k_to_35k.eitc_total@2024": 1856069552.630731,
    "irs_soi.ty2023.table_2_5.eitc_by_agi_children.no_qualifying_children.14k_to_15k.eitc_total@2024": 120240935.78285599,
    "irs_soi.ty2023.table_2_5.eitc_by_agi_children.no_qualifying_children.11k_to_12k.eitc_total@2024": 258361869.86322105,
    "irs_soi.ty2023.table_2_5.eitc_all_returns.total.total_earned_income_credit_amount@2024": 56642096387.45082,
    "irs_soi.ty2023.table_2_5.eitc_by_agi_children.one_qualifying_child.10k_to_11k.eitc_total@2024": 382109983.38895905,
    "irs_soi.ty2023.table_2_5.eitc_by_agi_children.one_qualifying_child.1k_to_2k.eitc_total@2024": 13867616.111499535,
    "irs_soi.ty2024.filing_season_week47.eitc_by_agi.30k_to_40k.total_earned_income_credit_amount@2024": 12078998311.703194,
    "irs_soi.ty2023.table_4_3.all_returns_excluding_dependents.all.taxable_interest_returns@2024": 80079093.22,
    "irs_soi.ty2023.table_2_5.eitc_by_agi_children.one_qualifying_child.19k_to_20k.eitc_returns@2024": 121744.79999999999,
    "irs_soi.ty2023.table_2_5.eitc_by_agi_children.two_qualifying_children.12k_to_13k.eitc_total@2024": 441190704.5403632,
    "irs_soi.ty2023.table_2_5.eitc_by_agi_children.three_or_more_qualifying_children.35k_to_40k.eitc_total@2024": 1840093819.7112975,
    "irs_soi.ty2023.table_2_5.eitc_by_agi_children.three_or_more_qualifying_children.2k_to_3k.eitc_total@2024": 12311827.853728212,
    "irs_soi.ty2023.table_2_5.eitc_by_agi_children.three_or_more_qualifying_children.19k_to_20k.eitc_returns@2024": 67580.7,
    "irs_soi.ty2023.table_2_5.eitc_by_agi_children.one_qualifying_child.8k_to_9k.eitc_total@2024": 263960724.60867447,
    "irs_soi.ty2023.table_2_5.eitc_by_agi_children.one_qualifying_child.40k_to_45k.eitc_total@2024": 555832578.2085992,
    "irs_soi.ty2024.filing_season_week47.eitc_by_agi.50k_to_75k.total_earned_income_credit_amount@2024": 1119344638.0928693,
    "irs_soi.ty2023.table_2_5.eitc_by_agi_children.two_qualifying_children.19k_to_20k.eitc_total@2024": 850032049.2643776,
    "irs_soi.ty2023.table_2_5.eitc_by_agi_children.one_qualifying_child.13k_to_14k.eitc_total@2024": 653190217.481956,
    "irs_soi.ty2024.filing_season_week47.eitc_by_agi.15k_to_20k.total_earned_income_credit_amount@2024": 9410545992.103561,
    "irs_soi.ty2023.table_2_5.eitc_by_agi_children.one_qualifying_child.14k_to_15k.eitc_total@2024": 781668609.7499288,
    "irs_soi.ty2023.table_2_5.eitc_by_agi_children.two_qualifying_children.10k_to_11k.eitc_total@2024": 273087464.8719192,
    "irs_soi.ty2022.historic_table_2.us.under_1.taxable_interest_amount@2024": 437551592.85383296,
    "irs_soi.ty2023.table_2_5.eitc_by_agi_children.one_qualifying_child.5k_to_6k.eitc_total@2024": 78115061.30017596,
    "irs_soi.ty2023.table_2_5.eitc_by_agi_children.two_qualifying_children.35k_to_40k.eitc_total@2024": 1929180033.0643897,
    "irs_soi.ty2023.table_2_5.eitc_by_agi_children.three_or_more_qualifying_children.11k_to_12k.eitc_total@2024": 182198796.04333365,
    "irs_soi.ty2023.table_2_5.eitc_by_agi_children.one_qualifying_child.25k_to_30k.eitc_total@2024": 2385712664.8494253,
    "irs_soi.ty2023.table_2_5.eitc_by_agi_children.no_qualifying_children.12k_to_13k.eitc_total@2024": 220799537.71553218,
    "irs_soi.ty2023.table_2_5.eitc_by_agi_children.no_qualifying_children.2k_to_3k.eitc_total@2024": 25200548.265011504,
    "irs_soi.ty2023.table_2_5.eitc_by_agi_children.three_or_more_qualifying_children.15k_to_16k.eitc_total@2024": 485594520.8385788,
    "irs_soi.ty2023.table_1_4.all.taxable_social_security_returns@2024": 33840964.55,
    "irs_soi.ty2023.table_2_5.eitc_by_agi_children.one_qualifying_child.15k_to_16k.eitc_returns@2024": 142727.27,
    "irs_soi.ty2023.table_2_5.eitc_by_agi_children.two_qualifying_children.1k_to_2k.eitc_total@2024": 10660064.74303063,
    "irs_soi.ty2023.table_2_5.eitc_by_agi_children.three_or_more_qualifying_children.14k_to_15k.eitc_total@2024": 294060405.5467201,
    "irs_soi.ty2023.table_2_5.eitc_by_agi_children.two_qualifying_children.7k_to_8k.eitc_total@2024": 83291531.44667085,
    "irs_soi.ty2023.table_2_5.eitc_by_agi_children.one_qualifying_child.18k_to_19k.eitc_returns@2024": 124023.29000000001,
    "irs_soi.ty2023.congressional_district_2022.all_returns.us.charitable_amount@2024": 213785321177.77176,
    "irs_soi.ty2023.table_2_5.eitc_by_agi_children.one_qualifying_child.11k_to_12k.eitc_total@2024": 420609050.67768043,
    "irs_soi.ty2023.table_1_4.all.wages_salaries_amount@2024": 11148390397432.432,
    "irs_soi.ty2023.table_2_5.eitc_all_returns.total.total_earned_income_credit_returns@2024": 18652628.46,
    "irs_soi.ty2023.table_1_4.all.taxable_pension_income_amount@2024": 914605906813.7653,
    "irs_soi.ty2022.historic_table_2.us.all.income_tax_before_credits_amount@2024": 2049398528771.7012,
    "irs_soi.ty2023.table_2_5.eitc_by_agi_children.three_or_more_qualifying_children.13k_to_14k.eitc_total@2024": 245124477.55894879,
    "irs_soi.ty2022.historic_table_2.us.all.qualified_dividends_amount@2024": 351758022938.7369,
    "irs_soi.ty2023.table_2_5.eitc_by_agi_children.three_or_more_qualifying_children.45k_to_50k.eitc_total@2024": 699170266.7419332,
    "irs_soi.ty2023.table_1_2.all_returns.all.taxable_income_amount@2024": 11562545285654.184,
    "irs_soi.ty2023.table_2_5.eitc_by_agi_children.no_qualifying_children.4k_to_5k.eitc_total@2024": 67603271.3209246,
    "irs_soi.ty2023.table_2_5.eitc_by_agi_children.two_qualifying_children.13k_to_14k.eitc_total@2024": 363582820.2767075,
    "irs_soi.ty2023.table_1_4.all.unemployment_compensation_amount@2024": 30993180447.079414,
    "irs_soi.ty2023.table_4_3.all_returns_excluding_dependents.all.taxable_income_amount@2024": 11562545285654.184,
    "irs_soi.ty2023.table_2_5.eitc_by_agi_children.one_qualifying_child.12k_to_13k.eitc_total@2024": 536534509.9741994,
    "irs_soi.ty2023.table_2_5.eitc_by_agi_children.two_qualifying_children.9k_to_10k.eitc_total@2024": 206182427.6675894,
    "irs_soi.ty2024.filing_season_week47.eitc_by_agi.10k_to_15k.total_earned_income_credit_amount@2024": 6782128030.290082,
    "irs_soi.ty2023.table_2_5.eitc_by_agi_children.one_qualifying_child.16k_to_17k.eitc_total@2024": 660834038.5057981,
    "irs_soi.ty2023.table_2_5.eitc_by_agi_children.no_qualifying_children.9k_to_10k.eitc_total@2024": 294190877.6227453,
    "irs_soi.ty2023.table_1_1.all.adjusted_gross_income@2024": 15231497698757.934,
    "irs_soi.ty2023.table_1_2.all_returns.all.adjusted_gross_income@2024": 15231497698757.934,
    "irs_soi.ty2023.table_2_5.eitc_by_agi_children.two_qualifying_children.4k_to_5k.eitc_total@2024": 58123525.990561426,
    "irs_soi.ty2023.table_2_5.eitc_by_agi_children.no_qualifying_children.5k_to_6k.eitc_total@2024": 82288943.50826445,
    "irs_soi.ty2023.table_2_5.eitc_by_agi_children.no_qualifying_children.8k_to_9k.eitc_total@2024": 261748613.86636013,
    "irs_soi.ty2023.table_2_5.eitc_by_agi_children.three_or_more_qualifying_children.16k_to_17k.eitc_total@2024": 554613921.2977511,
    "irs_soi.ty2023.congressional_district_2022.all_returns.us.income_tax_liability_amount@2024": 1867752959406.6704,
    "irs_soi.ty2024.filing_season_week47.eitc_by_agi.1_to_5k.total_earned_income_credit_returns@2024": 1025823.1799999999,
    "irs_soi.ty2023.congressional_district_2022.all_returns.us.adjusted_gross_income@2024": 15231497698757.934,
    "irs_soi.ty2023.table_2_1.itemized_all_returns.all.taxable_interest_amount@2024": 61384222015.499084,
    "irs_soi.ty2023.congressional_district_2022.all_returns.us.eitc_one_child_amount@2024": 16053661548.400658,
    "irs_soi.ty2023.table_4_3.all_returns_excluding_dependents.all.adjusted_gross_income@2024": 15231497698757.934,
    "irs_soi.ty2023.table_2_5.eitc_by_agi_children.no_qualifying_children.under_1.eitc_total@2024": 3500379.522047816,
    "irs_soi.ty2023.congressional_district_2022.all_returns.us.medical_dental_expense_amount@2024": 109949115115.76337,
    "irs_soi.ty2023.table_2_5.eitc_by_agi_children.two_qualifying_children.11k_to_12k.eitc_total@2024": 278596260.3347817,
    "irs_soi.ty2024.filing_season_week47.eitc_all_returns.earned_income_credit.total_earned_income_credit_returns@2024": 18652628.46,
    "irs_soi.ty2022.historic_table_2.us.1_to_10k.taxable_interest_returns@2024": 11737328.75,
    "irs_soi.ty2023.table_4_3.all_returns_excluding_dependents.all.taxable_interest_amount@2024": 115299057294.62277,
    "irs_soi.ty2023.table_2_1.itemized_all_returns.all.charitable_amount@2024": 213785321177.77176,
    "irs_soi.ty2023.congressional_district_2022.all_returns.us.schedule_c_income_amount@2024": 569326080092.5857,
    "irs_soi.ty2023.table_2_5.eitc_by_agi_children.one_qualifying_child.7k_to_8k.eitc_total@2024": 204512476.0048983,
    "irs_soi.ty2023.table_2_5.eitc_by_agi_children.two_qualifying_children.40k_to_45k.eitc_total@2024": 1196292547.069671,
    "irs_soi.ty2023.table_2_5.eitc_by_agi_children.three_or_more_qualifying_children.5k_to_6k.eitc_total@2024": 36849579.06781697,
    "irs_soi.ty2022.historic_table_2.us.all.taxable_income_amount@2024": 11562545285654.184,
    "irs_soi.ty2022.historic_table_2.us.all.schedule_c_income_returns@2024": 11509600.91,
    "irs_soi.ty2023.congressional_district_2022.all_returns.us.qualified_dividends_amount@2024": 351758022938.7369,
    "irs_soi.ty2023.congressional_district_2022.all_returns.us.eitc_amount@2024": 56642096387.45082,
    "irs_soi.ty2022.historic_table_2.us.all.actc_claims@2024": 16411109.489999998,
    "irs_soi.ty2023.table_1_4.all.unemployment_compensation_returns@2024": 11207503.559999999,
    "irs_soi.ty2023.state_2022.us.eitc_three_or_more_children_returns.three_or_more_qualifying_children.return_count@2024": 3124184.29,
    "irs_soi.ty2022.historic_table_2.us.all.taxable_interest_returns@2024": 80079093.22,
    "irs_soi.ty2022.historic_table_2.us.all.income_tax_before_credits_returns@2024": 130547289.82,
    "irs_soi.ty2022.historic_table_2.us.all.eitc_claims@2024": 18652628.46,
    "irs_soi.ty2023.table_2_1.itemized_all_returns.all.charitable_returns@2024": 21777627.79,
    "irs_soi.ty2023.congressional_district_2022.all_returns.us.eitc_two_children_amount@2024": 20894073297.705696,
    "irs_soi.ty2023.congressional_district_2022.all_returns.us.eitc_three_or_more_children_amount@2024": 17053488138.67209,
    "irs_soi.ty2023.congressional_district_2022.all_returns.us.income_tax_before_credits_amount@2024": 2049398528771.7012,
    "irs_soi.ty2024.filing_season_week47.eitc_by_agi.5k_to_10k.total_earned_income_credit_amount@2024": 2921159992.0582113,
    "irs_soi.ty2022.historic_table_2.us.all.actc_amount@2024": 35546160558.65372,
    "irs_soi.ty2022.historic_table_2.us.all.taxable_pension_income_returns@2024": 26596462.339999996,
    "irs_soi.ty2023.table_2_5.eitc_by_agi_children.one_qualifying_child.17k_to_18k.eitc_returns@2024": 120655.29000000001,
    "irs_soi.ty2022.historic_table_2.us.all.taxable_income_returns@2024": 132504680.99000001,
    "irs_soi.ty2023.table_1_4.all.wages_salaries_returns@2024": 137897938.09,
    "irs_soi.ty2022.historic_table_2.us.all.qualified_dividends_returns@2024": 23991871.19,
    "irs_soi.ty2023.table_2_5.eitc_by_agi_children.two_qualifying_children.15k_to_16k.eitc_total@2024": 574479812.6473272,
    "irs_soi.ty2023.congressional_district_2022.all_returns.us.unemployment_compensation_amount@2024": 30993180447.079414,
    "irs_soi.ty2023.table_2_5.eitc_by_agi_children.two_qualifying_children.14k_to_15k.eitc_total@2024": 426590005.0182031,
    "irs_soi.ty2022.historic_table_2.us.all.taxable_pension_income_amount@2024": 914605906813.7653,
    "irs_soi.ty2023.table_2_5.eitc_by_agi_children.two_qualifying_children.18k_to_19k.eitc_returns@2024": 107327.67000000001,
    "irs_soi.ty2023.table_2_5.eitc_by_agi_children.two_qualifying_children.5k_to_6k.eitc_total@2024": 58309023.372243926,
    "irs_soi.ty2022.historic_table_2.us.all.income_tax_liability_returns@2024": 141286313.57999998,
    "irs_soi.ty2023.table_2_5.eitc_all_returns.total.adjusted_gross_income@2024": 419790142993.931,
    "irs_soi.ty2023.table_2_5.eitc_by_agi_children.three_or_more_qualifying_children.3k_to_4k.eitc_returns@2024": 16627.86,
    "irs_soi.ty2023.congressional_district_2022.all_returns.us.actc_amount@2024": 35546160558.65372,
    "irs_soi.ty2022.historic_table_2.us.all.unemployment_compensation_amount@2024": 30993180447.079414,
    "irs_soi.ty2023.table_2_5.eitc_by_agi_children.one_qualifying_child.under_1.eitc_total@2024": 3402137.1010082867,
    "irs_soi.ty2023.congressional_district_2022.all_returns.us.unemployment_compensation_returns@2024": 11207503.559999999,
    "irs_soi.ty2023.congressional_district_2022.all_returns.us.medical_dental_expense_returns@2024": 3748785.33,
    "irs_soi.ty2022.historic_table_2.us.all.medical_dental_expense_returns@2024": 3748785.33,
    "irs_soi.ty2023.table_2_5.eitc_by_agi_children.one_qualifying_child.under_1.eitc_returns@2024": 3181.97,
    "irs_soi.ty2023.congressional_district_2022.all_returns.us.qualified_dividends_returns@2024": 23991871.19,
    "irs_soi.ty2022.historic_table_2.us.all.unemployment_compensation_returns@2024": 11207503.559999999,
    "irs_soi.ty2023.congressional_district_2022.all_returns.us.income_tax_liability_returns@2024": 141286313.57999998,
    "irs_soi.ty2022.historic_table_2.us.all.taxable_social_security_returns@2024": 33840964.55,
    "irs_soi.ty2023.congressional_district_2022.all_returns.us.taxable_social_security_amount@2024": 625887711518.7126,
    "irs_soi.ty2023.table_2_5.eitc_by_agi_children.one_qualifying_child.4k_to_5k.eitc_total@2024": 89967360.00358033,
    "irs_soi.ty2023.table_2_5.eitc_by_agi_children.three_or_more_qualifying_children.2k_to_3k.eitc_returns@2024": 14157.92,
    "irs_soi.ty2023.congressional_district_2022.all_returns.us.taxable_social_security_returns@2024": 33840964.55,
    "irs_soi.ty2022.historic_table_2.us.all.wages_salaries_returns@2024": 137897938.09,
    "irs_soi.ty2023.table_2_5.eitc_by_agi_children.one_qualifying_child.16k_to_17k.eitc_returns@2024": 158804.86000000002,
    "irs_soi.ty2023.table_2_5.eitc_by_agi_children.two_qualifying_children.2k_to_3k.eitc_total@2024": 18767718.885447256,
    "irs_soi.ty2023.table_2_5.eitc_by_agi_children.three_or_more_qualifying_children.6k_to_7k.eitc_total@2024": 69246979.38859794,
    "irs_soi.ty2023.congressional_district_2022.all_returns.us.taxable_pension_income_amount@2024": 914605906813.7653,
    "irs_soi.ty2023.table_2_5.eitc_by_agi_children.three_or_more_qualifying_children.17k_to_18k.eitc_total@2024": 609180280.0383136,
    "irs_soi.ty2023.table_2_5.eitc_by_agi_children.no_qualifying_children.19k_to_20k.eitc_returns@2024": 72153.9,
    "irs_soi.ty2023.table_2_5.eitc_by_agi_children.three_or_more_qualifying_children.17k_to_18k.eitc_returns@2024": 79966.43999999997,
    "irs_soi.ty2022.historic_table_2.us.all.taxable_social_security_amount@2024": 625887711518.7126,
    "irs_soi.ty2023.table_2_5.eitc_by_agi_children.one_qualifying_child.3k_to_4k.eitc_total@2024": 38947331.257240444,
    "irs_soi.ty2023.table_2_5.eitc_by_agi_children.three_or_more_qualifying_children.13k_to_14k.eitc_returns@2024": 44120.369999999995,
    "irs_soi.ty2023.table_4_3.all_returns_excluding_dependents.all.taxable_income_returns@2024": 132504680.99000001,
    "irs_soi.ty2023.table_2_5.eitc_by_agi_children.three_or_more_qualifying_children.12k_to_13k.eitc_total@2024": 214238015.54120275,
    "irs_soi.ty2023.table_2_5.eitc_by_agi_children.one_qualifying_child.1_to_1k.eitc_returns@2024": 21868.32,
    "irs_soi.ty2023.table_2_5.eitc_by_agi_children.two_qualifying_children.5k_to_6k.eitc_returns@2024": 29176.980000000003,
    "irs_soi.ty2023.table_2_5.eitc_by_agi_children.two_qualifying_children.1_to_1k.eitc_total@2024": 4906015.6329065105,
    "irs_soi.ty2023.table_2_5.eitc_by_agi_children.one_qualifying_child.7k_to_8k.eitc_returns@2024": 83700.03,
    "irs_soi.ty2023.table_2_5.eitc_by_agi_children.two_qualifying_children.25k_to_30k.eitc_returns@2024": 594303.31,
    "irs_soi.ty2023.table_2_5.eitc_by_agi_children.two_qualifying_children.1k_to_2k.eitc_returns@2024": 17468.579999999998,
    "irs_soi.ty2023.table_2_5.eitc_by_agi_children.one_qualifying_child.14k_to_15k.eitc_returns@2024": 187167.58000000002,
    "irs_soi.ty2023.table_2_5.eitc_by_agi_children.one_qualifying_child.3k_to_4k.eitc_returns@2024": 33508.1,
    "irs_soi.ty2023.table_2_5.eitc_by_agi_children.three_or_more_qualifying_children.under_1.eitc_returns@2024": 4677.17,
    "irs_soi.ty2023.table_2_5.eitc_by_agi_children.three_or_more_qualifying_children.14k_to_15k.eitc_returns@2024": 46943.85999999999,
    "irs_soi.ty2023.table_2_5.eitc_by_agi_children.no_qualifying_children.3k_to_4k.eitc_returns@2024": 117811.16000000002,
    "irs_soi.ty2023.table_2_5.eitc_by_agi_children.two_qualifying_children.50k_plus.eitc_total@2024": 440743198.9966869,
    "irs_soi.ty2023.congressional_district_2022.all_returns.us.actc_claims@2024": 16411109.489999998,
    "irs_soi.ty2022.historic_table_2.us.all.medical_dental_expense_amount@2024": 109949115115.76337,
    "irs_soi.ty2023.table_2_5.eitc_by_agi_children.two_qualifying_children.8k_to_9k.eitc_total@2024": 89856045.07923764,
    "irs_soi.ty2023.table_2_5.eitc_by_agi_children.two_qualifying_children.under_1.eitc_total@2024": 4515626.048247666,
    "irs_soi.ty2022.historic_table_2.us.75k_to_100k.taxable_interest_returns@2024": 8464911.56,
    "irs_soi.ty2023.table_2_5.eitc_by_agi_children.no_qualifying_children.8k_to_9k.eitc_returns@2024": 431950.24,
    "irs_soi.ty2023.table_2_5.eitc_by_agi_children.three_or_more_qualifying_children.6k_to_7k.eitc_returns@2024": 24508.88,
    "irs_soi.ty2023.table_2_5.eitc_by_agi_children.no_qualifying_children.7k_to_8k.eitc_total@2024": 234492339.8958267,
    "irs_soi.ty2023.table_2_5.eitc_by_agi_children.one_qualifying_child.12k_to_13k.eitc_returns@2024": 130079.65000000001,
    "irs_soi.ty2023.table_2_5.eitc_by_agi_children.one_qualifying_child.25k_to_30k.eitc_returns@2024": 658666.0,
    "irs_soi.ty2023.table_2_5.eitc_by_agi_children.three_or_more_qualifying_children.12k_to_13k.eitc_returns@2024": 41138.30000000001,
    "irs_soi.ty2023.table_2_5.eitc_by_agi_children.three_or_more_qualifying_children.9k_to_10k.eitc_total@2024": 150016242.37389794,
    "irs_soi.ty2022.historic_table_2.us.10k_to_25k.taxable_interest_returns@2024": 6928011.02,
    "irs_soi.ty2023.table_2_5.eitc_by_agi_children.no_qualifying_children.1k_to_2k.eitc_returns@2024": 116699.23999999999,
    "irs_soi.ty2023.table_2_5.eitc_by_agi_children.three_or_more_qualifying_children.7k_to_8k.eitc_total@2024": 131937177.89681205,
    "irs_soi.ty2023.table_2_5.eitc_by_agi_children.three_or_more_qualifying_children.16k_to_17k.eitc_returns@2024": 76587.97,
    "irs_soi.ty2023.table_2_5.eitc_by_agi_children.no_qualifying_children.17k_to_18k.eitc_returns@2024": 223191.72999999998,
    "irs_soi.ty2023.table_2_5.eitc_by_agi_children.no_qualifying_children.3k_to_4k.eitc_total@2024": 31285029.68416079,
    "irs_soi.ty2023.table_2_5.eitc_by_agi_children.three_or_more_qualifying_children.10k_to_11k.eitc_returns@2024": 41915.76,
    "irs_soi.ty2024.filing_season_week47.eitc_by_agi.under_1.total_earned_income_credit_returns@2024": 24549.199999999997,
    "irs_soi.ty2023.table_2_5.eitc_by_agi_children.no_qualifying_children.6k_to_7k.eitc_returns@2024": 336645.41,
    "irs_soi.ty2023.table_2_5.eitc_by_agi_children.one_qualifying_child.17k_to_18k.eitc_total@2024": 506316849.22032857,
    "irs_soi.ty2023.table_2_5.eitc_by_agi_children.two_qualifying_children.6k_to_7k.eitc_returns@2024": 50637.67999999999,
    "irs_soi.ty2022.historic_table_2.us.all.adjusted_gross_income@2024": 15231497698757.934,
    "irs_soi.ty2023.table_2_5.eitc_by_agi_children.one_qualifying_child.2k_to_3k.eitc_returns@2024": 48536.15,
    "irs_soi.ty2023.table_2_5.eitc_by_agi_children.no_qualifying_children.9k_to_10k.eitc_returns@2024": 480494.25,
    "irs_soi.ty2023.table_2_5.eitc_by_agi_children.no_qualifying_children.4k_to_5k.eitc_returns@2024": 193386.90000000002,
    "irs_soi.ty2023.table_2_5.eitc_by_agi_children.three_or_more_qualifying_children.9k_to_10k.eitc_returns@2024": 36915.3,
    "irs_soi.ty2024.filing_season_week47.eitc_by_agi.under_1.total_earned_income_credit_amount@2024": 17381292.74377133,
    "irs_soi.ty2023.table_2_5.eitc_by_agi_children.no_qualifying_children.6k_to_7k.eitc_total@2024": 162527265.8204633,
    "irs_soi.ty2022.historic_table_2.us.50k_to_75k.taxable_interest_returns@2024": 10173133.58,
    "irs_soi.ty2023.congressional_district_2022.all_returns.us.eitc_one_child_claims@2024": 5193165.37,
    "irs_soi.ty2023.table_2_5.eitc_by_agi_children.no_qualifying_children.1_to_1k.eitc_total@2024": 4727876.109552816,
    "irs_soi.ty2023.table_2_5.eitc_by_agi_children.two_qualifying_children.50k_plus.eitc_returns@2024": 381435.12000000005,
    "irs_soi.ty2022.historic_table_2.us.200k_to_500k.taxable_interest_returns@2024": 10221244.43,
    "irs_soi.ty2023.table_2_5.eitc_by_agi_children.one_qualifying_child.4k_to_5k.eitc_returns@2024": 61221.619999999995,
    "irs_soi.ty2023.table_2_5.eitc_by_agi_children.three_or_more_qualifying_children.11k_to_12k.eitc_returns@2024": 38105.83000000001,
    "irs_soi.ty2023.table_2_5.eitc_by_agi_children.no_qualifying_children.11k_to_12k.eitc_returns@2024": 477815.32,
    "irs_soi.ty2023.congressional_district_2022.all_returns.us.taxable_pension_income_returns@2024": 26596462.339999996,
    "irs_soi.ty2023.table_2_5.eitc_by_agi_children.three_or_more_qualifying_children.35k_to_40k.eitc_returns@2024": 332062.0,
    "irs_soi.ty2023.table_2_5.eitc_by_agi_children.two_qualifying_children.12k_to_13k.eitc_returns@2024": 90566.09,
    "irs_soi.ty2023.table_2_5.eitc_by_agi_children.one_qualifying_child.8k_to_9k.eitc_returns@2024": 91440.52,
    "irs_soi.ty2023.table_2_5.eitc_by_agi_children.three_or_more_qualifying_children.8k_to_9k.eitc_returns@2024": 19798.459999999995,
    "irs_soi.ty2023.table_2_5.eitc_by_agi_children.three_or_more_qualifying_children.10k_to_11k.eitc_total@2024": 192521764.26573217,
    "irs_soi.ty2023.table_2_5.eitc_by_agi_children.two_qualifying_children.10k_to_11k.eitc_returns@2024": 66772.09999999999,
    "irs_soi.ty2023.table_2_5.eitc_by_agi_children.no_qualifying_children.7k_to_8k.eitc_returns@2024": 423962.99,
    "irs_soi.ty2023.table_2_5.eitc_by_agi_children.three_or_more_qualifying_children.under_1.eitc_total@2024": 5963150.07246756,
    "irs_soi.ty2023.table_2_5.eitc_by_agi_children.two_qualifying_children.8k_to_9k.eitc_returns@2024": 27463.260000000002,
    "irs_soi.ty2023.table_2_5.eitc_by_agi_children.three_or_more_qualifying_children.5k_to_6k.eitc_returns@2024": 17003.620000000003,
    "irs_soi.ty2024.filing_season_week47.eitc_by_agi.25k_to_30k.total_earned_income_credit_returns@2024": 1669293.48,
    "irs_soi.ty2023.congressional_district_2022.all_returns.us.taxable_interest_returns@2024": 80079093.22,
    "irs_soi.ty2023.table_2_5.eitc_by_agi_children.two_qualifying_children.11k_to_12k.eitc_returns@2024": 61853.43,
    "irs_soi.ty2023.table_2_5.eitc_by_agi_children.no_qualifying_children.16k_to_17k.eitc_returns@2024": 266099.14,
    "irs_soi.ty2023.table_2_5.eitc_by_agi_children.no_qualifying_children.2k_to_3k.eitc_returns@2024": 122726.25,
    "irs_soi.ty2023.table_2_5.eitc_by_agi_children.one_qualifying_child.1k_to_2k.eitc_returns@2024": 25263.319999999996,
    "irs_soi.ty2023.table_2_5.eitc_by_agi_children.three_or_more_qualifying_children.7k_to_8k.eitc_returns@2024": 40256.51000000001,
    "irs_soi.ty2023.table_2_5.eitc_by_agi_children.no_qualifying_children.15k_to_16k.eitc_returns@2024": 331453.20000000007,
    "irs_soi.ty2023.table_2_5.eitc_by_agi_children.two_qualifying_children.13k_to_14k.eitc_returns@2024": 68465.48000000003,
    "irs_soi.ty2023.congressional_district_2022.all_returns.us.income_tax_before_credits_returns@2024": 130547289.82,
    "irs_soi.ty2023.table_2_5.eitc_by_agi_children.one_qualifying_child.45k_to_50k.eitc_returns@2024": 252369.06000000006,
    "irs_soi.ty2022.historic_table_2.us.all.schedule_c_income_amount@2024": 569326080092.5857,
    "irs_soi.ty2023.table_2_5.eitc_by_agi_children.one_qualifying_child.15k_to_16k.eitc_total@2024": 599398214.2511148,
    "irs_soi.ty2024.filing_season_week47.eitc_by_agi.50k_to_75k.total_earned_income_credit_returns@2024": 906022.3900000001,
    "irs_soi.ty2023.table_2_5.eitc_by_agi_children.no_qualifying_children.10k_to_11k.eitc_total@2024": 303570433.1781638,
    "irs_soi.ty2023.table_2_5.eitc_by_agi_children.three_or_more_qualifying_children.18k_to_19k.eitc_total@2024": 570130158.7388041,
    "irs_soi.ty2023.table_2_5.eitc_by_agi_children.one_qualifying_child.45k_to_50k.eitc_total@2024": 179587326.957184,
    "irs_soi.ty2023.table_2_5.eitc_by_agi_children.two_qualifying_children.45k_to_50k.eitc_total@2024": 563528046.0066638,
    "irs_soi.ty2023.table_2_1.itemized_all_returns.all.taxable_pension_income_amount@2024": 180475775924.04266,
    "irs_soi.ty2023.table_2_5.eitc_by_agi_children.one_qualifying_child.13k_to_14k.eitc_returns@2024": 158103.94,
    "irs_soi.ty2023.table_2_5.eitc_by_agi_children.three_or_more_qualifying_children.4k_to_5k.eitc_total@2024": 23395194.893108554,
    "irs_soi.ty2023.table_2_5.eitc_by_agi_children.three_or_more_qualifying_children.45k_to_50k.eitc_returns@2024": 192534.61000000002,
    "irs_soi.ty2023.table_2_5.eitc_by_agi_children.two_qualifying_children.under_1.eitc_returns@2024": 884.6,
    "irs_soi.ty2023.table_2_5.eitc_by_agi_children.one_qualifying_child.50k_plus.eitc_total@2024": 60912042.40320867,
    "irs_soi.ty2023.table_2_5.eitc_by_agi_children.one_qualifying_child.6k_to_7k.eitc_total@2024": 139687175.8522854,
    "irs_soi.ty2023.table_2_5.eitc_by_agi_children.one_qualifying_child.35k_to_40k.eitc_returns@2024": 488575.86,
    "irs_soi.ty2023.table_2_5.eitc_by_agi_children.two_qualifying_children.35k_to_40k.eitc_returns@2024": 420988.28,
    "irs_soi.ty2023.congressional_district_2022.all_returns.us.eitc_no_children_amount@2024": 2640873402.672373,
    "irs_soi.ty2023.table_2_5.eitc_by_agi_children.one_qualifying_child.19k_to_20k.eitc_total@2024": 511831297.74551105,
    "irs_soi.ty2023.table_2_5.eitc_by_agi_children.no_qualifying_children.5k_to_6k.eitc_returns@2024": 198196.63,
    "irs_soi.ty2023.table_2_5.eitc_by_agi_children.one_qualifying_child.10k_to_11k.eitc_returns@2024": 111893.26999999999,
    "irs_soi.ty2024.filing_season_week47.eitc_by_agi.10k_to_15k.total_earned_income_credit_returns@2024": 3500735.68,
    "irs_soi.ty2023.congressional_district_2022.all_returns.us.eitc_claims@2024": 18652628.46,
    "irs_soi.ty2023.congressional_district_2022.all_returns.us.eitc_three_or_more_children_claims@2024": 3124184.29,
    "irs_soi.ty2023.table_2_5.eitc_by_agi_children.one_qualifying_child.30k_to_35k.eitc_returns@2024": 603058.03,
    "irs_soi.ty2023.table_2_5.eitc_by_agi_children.two_qualifying_children.30k_to_35k.eitc_returns@2024": 522770.20000000007,
    "irs_soi.ty2023.table_2_5.eitc_by_agi_children.no_qualifying_children.under_1.eitc_returns@2024": 15805.46,
    "irs_soi.ty2023.table_2_5.eitc_by_agi_children.two_qualifying_children.7k_to_8k.eitc_returns@2024": 29556.200000000004,
    "irs_soi.ty2023.table_2_5.eitc_by_agi_children.three_or_more_qualifying_children.50k_plus.eitc_returns@2024": 394553.70999999996,
    "irs_soi.ty2023.table_2_5.eitc_by_agi_children.two_qualifying_children.1_to_1k.eitc_returns@2024": 17454.28,
    "irs_soi.ty2023.table_2_5.eitc_by_agi_children.no_qualifying_children.13k_to_14k.eitc_returns@2024": 460579.31,
    "irs_soi.ty2023.table_2_5.eitc_by_agi_children.one_qualifying_child.6k_to_7k.eitc_returns@2024": 65512.93,
    "irs_soi.ty2023.table_2_5.eitc_by_agi_children.one_qualifying_child.35k_to_40k.eitc_total@2024": 1103648580.103519,
    "irs_soi.ty2023.table_2_1.itemized_all_returns.all.taxable_social_security_amount@2024": 88202484248.65396,
    "irs_soi.ty2023.table_2_5.eitc_by_agi_children.two_qualifying_children.15k_to_16k.eitc_returns@2024": 95259.90000000001,
    "irs_soi.ty2023.table_2_5.eitc_by_agi_children.no_qualifying_children.1k_to_2k.eitc_total@2024": 15625105.032206513,
    "irs_soi.ty2023.table_2_5.eitc_by_agi_children.two_qualifying_children.14k_to_15k.eitc_returns@2024": 74131.64,
    "irs_soi.ty2023.table_2_5.eitc_by_agi_children.no_qualifying_children.14k_to_15k.eitc_returns@2024": 319969.26,
    "irs_soi.ty2023.table_2_1.itemized_all_returns.all.taxable_pension_income_returns@2024": 3354956.3000000003,
    "irs_soi.ty2023.table_2_5.eitc_by_agi_children.two_qualifying_children.4k_to_5k.eitc_returns@2024": 33445.44,
    "irs_soi.ty2023.table_2_5.eitc_by_agi_children.two_qualifying_children.19k_to_20k.eitc_returns@2024": 125250.78,
    "irs_soi.ty2023.congressional_district_2022.all_returns.us.schedule_c_income_returns@2024": 11509600.91,
    "irs_soi.ty2023.table_2_5.eitc_by_agi_children.three_or_more_qualifying_children.8k_to_9k.eitc_total@2024": 71788208.55395861,
    "irs_soi.ty2023.congressional_district_2022.all_returns.us.charitable_returns@2024": 21777627.79,
    "irs_soi.ty2023.table_2_5.eitc_by_agi_children.three_or_more_qualifying_children.40k_to_45k.eitc_returns@2024": 237128.91,
    "irs_soi.ty2023.table_2_5.eitc_by_agi_children.three_or_more_qualifying_children.19k_to_20k.eitc_total@2024": 525971426.21794486,
    "irs_soi.ty2023.congressional_district_2022.all_returns.us.eitc_no_children_claims@2024": 6029278.09,
    "irs_soi.ty2023.congressional_district_2022.all_returns.us.eitc_two_children_claims@2024": 4306000.71,
    "irs_soi.ty2023.table_2_5.eitc_by_agi_children.one_qualifying_child.9k_to_10k.eitc_returns@2024": 61752.450000000004,
    "irs_soi.ty2023.table_2_5.eitc_by_agi_children.two_qualifying_children.18k_to_19k.eitc_total@2024": 729168632.2134647,
    "irs_soi.ty2023.table_2_5.eitc_by_agi_children.no_qualifying_children.12k_to_13k.eitc_returns@2024": 458742.88,
    "irs_soi.ty2023.table_2_5.eitc_by_agi_children.no_qualifying_children.10k_to_11k.eitc_returns@2024": 510537.54,
    "irs_soi.ty2023.table_2_5.eitc_by_agi_children.no_qualifying_children.20k_to_25k.eitc_returns@2024": 191910.51999999996,
    "irs_soi.ty2023.table_2_5.eitc_by_agi_children.one_qualifying_child.18k_to_19k.eitc_total@2024": 520996367.8679963,
    "irs_soi.ty2024.filing_season_week47.eitc_by_agi.40k_to_50k.total_earned_income_credit_amount@2024": 4287127789.202746,
    "irs_soi.ty2023.table_2_5.eitc_by_agi_children.one_qualifying_child.40k_to_45k.eitc_returns@2024": 357847.04,
    "irs_soi.ty2023.table_2_5.eitc_by_agi_children.two_qualifying_children.45k_to_50k.eitc_returns@2024": 229439.82,
    "irs_soi.ty2023.table_2_5.eitc_by_agi_children.two_qualifying_children.9k_to_10k.eitc_returns@2024": 51291.450000000004,
    "irs_soi.ty2024.filing_season_week47.eitc_by_agi.40k_to_50k.total_earned_income_credit_returns@2024": 1606412.12,
    "irs_soi.ty2023.table_2_5.eitc_by_agi_children.no_qualifying_children.18k_to_19k.eitc_total@2024": 42756282.73522104,
    "irs_soi.ty2022.historic_table_2.us.500k_to_1m.taxable_interest_returns@2024": 1276527.47,
    "irs_soi.ty2024.filing_season_week47.eitc_by_agi.15k_to_20k.total_earned_income_credit_returns@2024": 2633257.63,
    "irs_soi.ty2023.table_2_1.itemized_all_returns.all.taxable_interest_returns@2024": 19657963.03,
    "irs_soi.ty2023.table_2_5.eitc_by_agi_children.three_or_more_qualifying_children.4k_to_5k.eitc_returns@2024": 13775.65,
    "irs_soi.ty2024.filing_season_week47.eitc_by_agi.30k_to_40k.total_earned_income_credit_returns@2024": 2747099.16,
    "irs_soi.ty2023.table_2_5.eitc_by_agi_children.one_qualifying_child.11k_to_12k.eitc_returns@2024": 111834.07,
    "irs_soi.ty2022.historic_table_2.us.all.wages_salaries_amount@2024": 11148390397432.432,
    "irs_soi.ty2023.table_2_5.eitc_by_agi_children.three_or_more_qualifying_children.40k_to_45k.eitc_total@2024": 1092717024.2186947,
    "irs_soi.ty2023.table_2_5.eitc_by_agi_children.one_qualifying_child.9k_to_10k.eitc_total@2024": 185274503.71523303,
    "irs_soi.ty2023.table_2_1.itemized_all_returns.all.adjusted_gross_income@2024": 6230359455698.602,
    "irs_soi.ty2023.table_2_5.eitc_by_agi_children.one_qualifying_child.50k_plus.eitc_returns@2024": 130033.56,
    "irs_soi.ty2023.table_2_5.eitc_by_agi_children.no_qualifying_children.1_to_1k.eitc_returns@2024": 97726.47,
    "irs_soi.ty2023.table_2_5.eitc_by_agi_children.two_qualifying_children.2k_to_3k.eitc_returns@2024": 20958.15,
    "irs_soi.ty2023.table_2_5.eitc_by_agi_children.two_qualifying_children.3k_to_4k.eitc_total@2024": 30856213.13283682,
    "irs_soi.ty2023.table_2_5.eitc_by_agi_children.two_qualifying_children.3k_to_4k.eitc_returns@2024": 23724.760000000002,
    "irs_soi.ty2022.historic_table_2.us.25k_to_50k.taxable_interest_returns@2024": 10224501.75,
    "irs_soi.ty2022.historic_table_2.us.100k_to_200k.taxable_interest_returns@2024": 19774207.939999998,
    "irs_soi.ty2023.table_2_5.eitc_by_agi_children.three_or_more_qualifying_children.15k_to_16k.eitc_returns@2024": 69644.59999999999,
    "irs_soi.ty2022.historic_table_2.us.all.eitc_amount@2024": 56642096387.45082,
    "irs_soi.ty2024.filing_season_week47.eitc_by_agi.5k_to_10k.total_earned_income_credit_returns@2024": 2544864.09,
    "irs_soi.ty2024.filing_season_week47.eitc_by_agi.1_to_5k.total_earned_income_credit_amount@2024": 532879268.7752077,
    "irs_soi.ty2022.historic_table_2.us.all.income_tax_liability_amount@2024": 1867752959406.6704,
    "irs_soi.ty2023.table_2_5.eitc_by_agi_children.two_qualifying_children.40k_to_45k.eitc_returns@2024": 337092.68000000005,
    "irs_soi.ty2023.table_2_5.eitc_by_agi_children.two_qualifying_children.6k_to_7k.eitc_total@2024": 116884795.01645938,
    "irs_soi.ty2023.table_2_5.eitc_by_agi_children.three_or_more_qualifying_children.18k_to_19k.eitc_returns@2024": 73988.11,
    "irs_soi.ty2023.table_1_4.all.taxable_pension_income_returns@2024": 26596462.339999996,
    "irs_soi.ty2022.historic_table_2.us.under_1.taxable_interest_returns@2024": 714503.6900000001,
    "irs_soi.ty2023.table_2_1.itemized_all_returns.all.taxable_social_security_returns@2024": 3989699.3,
    "irs_soi.ty2023.table_2_5.eitc_by_agi_children.one_qualifying_child.5k_to_6k.eitc_returns@2024": 44600.3,
    "irs_soi.ty2024.filing_season_week47.eitc_by_agi.75k_to_100k.total_earned_income_credit_returns@2024": 0.0,
    "irs_soi.ty2024.filing_season_week47.eitc_by_agi.100k_to_200k.total_earned_income_credit_returns@2024": 0.0,
    "irs_soi.ty2024.filing_season_week47.eitc_by_agi.200k_to_250k.total_earned_income_credit_returns@2024": 0.0,
    "irs_soi.ty2024.filing_season_week47.eitc_by_agi.250k_to_500k.total_earned_income_credit_returns@2024": 0.0,
    "irs_soi.ty2024.filing_season_week47.eitc_by_agi.500k_to_1m.total_earned_income_credit_returns@2024": 0.0,
    "irs_soi.ty2024.filing_season_week47.eitc_by_agi.1m_plus.total_earned_income_credit_returns@2024": 0.0,
    "irs_soi.ty2024.filing_season_week47.eitc_by_agi.75k_to_100k.total_earned_income_credit_amount@2024": 0.0,
    "irs_soi.ty2024.filing_season_week47.eitc_by_agi.100k_to_200k.total_earned_income_credit_amount@2024": 0.0,
    "irs_soi.ty2024.filing_season_week47.eitc_by_agi.200k_to_250k.total_earned_income_credit_amount@2024": 0.0,
    "irs_soi.ty2024.filing_season_week47.eitc_by_agi.250k_to_500k.total_earned_income_credit_amount@2024": 0.0,
    "irs_soi.ty2024.filing_season_week47.eitc_by_agi.500k_to_1m.total_earned_income_credit_amount@2024": 0.0,
    "irs_soi.ty2024.filing_season_week47.eitc_by_agi.1m_plus.total_earned_income_credit_amount@2024": 0.0,
    "irs_soi.ty2023.table_2_5.eitc_by_agi_children.no_qualifying_children.25k_to_30k.eitc_returns@2024": 17384.480000000003,
    "irs_soi.ty2023.table_2_5.eitc_by_agi_children.no_qualifying_children.25k_to_30k.eitc_total@2024": 273949.495899347,
    "irs_soi.ty2023.table_2_5.eitc_by_agi_children.no_qualifying_children.30k_to_35k.eitc_returns@2024": 0.0,
    "irs_soi.ty2023.table_2_5.eitc_by_agi_children.no_qualifying_children.30k_to_35k.eitc_total@2024": 0.0,
    "irs_soi.ty2023.table_2_5.eitc_by_agi_children.no_qualifying_children.35k_to_40k.eitc_returns@2024": 0.0,
    "irs_soi.ty2023.table_2_5.eitc_by_agi_children.no_qualifying_children.35k_to_40k.eitc_total@2024": 0.0,
    "irs_soi.ty2023.table_2_5.eitc_by_agi_children.no_qualifying_children.40k_to_45k.eitc_returns@2024": 0.0,
    "irs_soi.ty2023.table_2_5.eitc_by_agi_children.no_qualifying_children.40k_to_45k.eitc_total@2024": 0.0,
    "irs_soi.ty2023.table_2_5.eitc_by_agi_children.no_qualifying_children.45k_to_50k.eitc_returns@2024": 0.0,
    "irs_soi.ty2023.table_2_5.eitc_by_agi_children.no_qualifying_children.45k_to_50k.eitc_total@2024": 0.0,
    "irs_soi.ty2023.table_2_5.eitc_by_agi_children.no_qualifying_children.50k_plus.eitc_returns@2024": 0.0,
    "irs_soi.ty2023.table_2_5.eitc_by_agi_children.no_qualifying_children.50k_plus.eitc_total@2024": 0.0,
    "irs_soi.ty2023.table_2_5.eitc_by_agi_children.three_or_more_qualifying_children.30k_to_35k.eitc_returns@2024": 379644.79,
    "irs_soi.ty2023.table_2_5.eitc_by_agi_children.three_or_more_qualifying_children.30k_to_35k.eitc_total@2024": 2473141859.4043727
  }
}